bit_audio_tag/__init__.py
bit_audio_tag/audio_file.py
bit_audio_tag/metadata.py
bit_audio_tag/handlers/__init__.py
bit_audio_tag/handlers/base.py
bit_audio_tag/handlers/flac_handler.py
bit_audio_tag/handlers/mp3_handler.py
bit_audio_tag/handlers/mp4_handler.py
bit_audio_tag/handlers/ogg_handler.py
bit_audio_tag-1.1.0.dist-info/licenses/LICENSE
bit_audio_tag-1.1.0.dist-info/METADATA
bit_audio_tag-1.1.0.dist-info/WHEEL
bit_audio_tag-1.1.0.dist-info/top_level.txt
bit_audio_tag-1.1.0.dist-info/RECORD
