Metadata-Version: 2.4
Name: bit_audio_tag
Version: 1.1.0
Summary: A package for audio tagging
Home-page: https://github.com/Bitliker/audio_tag
Author: Bitliker
Author-email: gongpengming@163.com
Classifier: Programming Language :: Python :: 3
Classifier: License :: OSI Approved :: MIT License
Classifier: Operating System :: OS Independent
Requires-Python: >=3.9
License-File: LICENSE
Requires-Dist: mutagen>=1.47.0
Dynamic: author
Dynamic: author-email
Dynamic: classifier
Dynamic: description
Dynamic: description-content-type
Dynamic: home-page
Dynamic: license-file
Dynamic: requires-dist
Dynamic: requires-python
Dynamic: summary
